cyheif
cyheifloader
