Metadata-Version: 2.1
Name: cyheif
Version: 0.0.2
Summary: Python wrapper for libheif
Home-page: https://github.com/ram-nat/CyHeif/
Author: Ramkumar Natarajan
License: UNKNOWN
Keywords: libheif,heif,heic,high-efficiency image format
Platform: UNKNOWN
Requires-Python: >=3.6
License-File: LICENSE.txt
